zhlib/__init__.py
zhlib/db.py
zhlib/dict.db
zhlib/freq.json
zhlib/level.py
zhlib/sentence.py
zhlib/util.py
zhlib-0.1.3.dist-info/WHEEL
zhlib-0.1.3.dist-info/METADATA
zhlib-0.1.3.dist-info/RECORD
